LICENSE
README.md
pyproject.toml
setup.cfg
setup.py
pymft/__init__.py
pymft/main.py
pymft.egg-info/PKG-INFO
pymft.egg-info/SOURCES.txt
pymft.egg-info/dependency_links.txt
pymft.egg-info/entry_points.txt
pymft.egg-info/requires.txt
pymft.egg-info/top_level.txt
pymft/src/__init__.py
pymft/src/config.py
pymft/src/constants.py
pymft/src/device_settings.py
pymft/src/encoder.py
pymft/src/knob_settings.py
pymft/src/pymft.py